README.md
setup.py
hackatari/__init__.py
hackatari/core.py
hackatari.egg-info/PKG-INFO
hackatari.egg-info/SOURCES.txt
hackatari.egg-info/dependency_links.txt
hackatari.egg-info/requires.txt
hackatari.egg-info/top_level.txt
hackatari/games/__init__.py
hackatari/games/amidar.py
hackatari/games/asterix.py
hackatari/games/atlantis.py
hackatari/games/bankheist.py
hackatari/games/boxing.py
hackatari/games/breakout.py
hackatari/games/carnival.py
hackatari/games/choppercommand.py
hackatari/games/demonattack.py
hackatari/games/donkeykong.py
hackatari/games/doubledunk.py
hackatari/games/fishingderby.py
hackatari/games/freeway.py
hackatari/games/frostbite.py
hackatari/games/kangaroo.py
hackatari/games/kungfumaster.py
hackatari/games/montezumarevenge.py
hackatari/games/mspacman.py
hackatari/games/namethisgame.py
hackatari/games/pong.py
hackatari/games/riverraid.py
hackatari/games/seaquest.py
hackatari/games/skiing.py
hackatari/games/spaceinvaders.py
hackatari/games/tennis.py
hackatari/games/venture.py
hackatari/games/yarsrevenge.py