Metadata-Version: 2.1
Name: hackatari
Version: 0.0.6
Summary: Extended Atari Learning Environments
Home-page: https://github.com/k4ntz/HAckAtari
Author: Quentin Delfosse, Jannis Blüml
Author-email: quentin.delfosse@cs.tu-darmstadt.de
